LICENSE
README.md
requirements-dev.txt
requirements.txt
setup.py
bintablefile/bintablefile.c
bintablefile/bintablefile.pyx
bintablefile.egg-info/PKG-INFO
bintablefile.egg-info/SOURCES.txt
bintablefile.egg-info/dependency_links.txt
bintablefile.egg-info/requires.txt
bintablefile.egg-info/top_level.txt
tests/test_bintablefile.py