Metadata-Version: 2.1
Name: bintablefile
Version: 2.2.4
Summary: Binary Table File - efficient binary file format to store and retrieve tabular data
Home-page: https://github.com/eSAMTrade/bintablefile
Author: andrei.suiu/marian.rusu
Requires-Python: >=3.7
License-File: LICENSE
Requires-Dist: numpy>=1.13.0
Requires-Dist: pandas>=0.23.0
Requires-Dist: pydantic>=1.6
Requires-Dist: pyxtension>=1.12
Requires-Dist: msgpack>=0.5.0
Provides-Extra: dev
Requires-Dist: cython; extra == "dev"
Requires-Dist: wheel; extra == "dev"
Requires-Dist: twine; extra == "dev"
Requires-Dist: python-idzip>=0.3.6; extra == "dev"
Requires-Dist: pydantic>=2.0.0; extra == "dev"
